{
    "backend": "flask",
    "db_name": "",
    "db_pass": "",
    "db_type": "sqlite",
    "db_user": "",
    "dbms": "1",
    "description": "generated product",
    "design": "datta-able",
    "docker": "0",
    "err_code": 0,
    "frontend": "",
    "heroku": "0",
    "pattern": "mvc",
    "pro": "0",
    "task_id": "a9a792dc-07fc-4202-b18b-e1f9d8dde29b",
    "task_info": "Upload Sources [0%] - 144 files",
    "task_output": "a9a792dc-07fc-4202-b18b-e1f9d8dde29b.zip",
    "task_result": "SUCCESS",
    "task_state": "RUNNING",
    "task_ts_end": "2024-02-18-14-28-06",
    "task_ts_start": "2024-02-18-14-28-05"
}